.gitignore
LICENSE
README.md
codemeta.json
setup.py
codemeta2html/codemeta2html.py
codemeta2html/html.py
codemeta2html.egg-info/PKG-INFO
codemeta2html.egg-info/SOURCES.txt
codemeta2html.egg-info/dependency_links.txt
codemeta2html.egg-info/entry_points.txt
codemeta2html.egg-info/not-zip-safe
codemeta2html.egg-info/requires.txt
codemeta2html.egg-info/top_level.txt
codemeta2html/style/alpine.min.js
codemeta2html/style/codemeta.css
codemeta2html/style/fa-brands-400.woff
codemeta2html/style/fa-brands-400.woff2
codemeta2html/style/fa-regular-400.woff
codemeta2html/style/fa-regular-400.woff2
codemeta2html/style/fa-solid-900.woff
codemeta2html/style/fa-solid-900.woff2
codemeta2html/style/fontawesome.css
codemeta2html/templates/badge.html
codemeta2html/templates/card_service.html
codemeta2html/templates/card_softwaresourcecode.html
codemeta2html/templates/cardindex.html
codemeta2html/templates/cardindex_body.html
codemeta2html/templates/citation.html
codemeta2html/templates/developmentstatus.html
codemeta2html/templates/filters.html
codemeta2html/templates/footer.html
codemeta2html/templates/generic.html
codemeta2html/templates/head.html
codemeta2html/templates/header.html
codemeta2html/templates/indexfooter.html
codemeta2html/templates/intro.html
codemeta2html/templates/iodata.html
codemeta2html/templates/page_generic.html
codemeta2html/templates/page_person_or_org.html
codemeta2html/templates/page_softwaresourcecode.html
codemeta2html/templates/page_targetproduct.html
codemeta2html/templates/person_or_org.html
codemeta2html/templates/person_or_org_minimal.html
codemeta2html/templates/redirect.html
codemeta2html/templates/reference.html
codemeta2html/templates/reference_author.html
codemeta2html/templates/serviceindex.html
codemeta2html/templates/servicetoc.html
codemeta2html/templates/softwaresourcecode.html
codemeta2html/templates/tableindex.html
codemeta2html/templates/tablerow_softwaresourcecode.html
codemeta2html/templates/tablerow_targetproduct.html
codemeta2html/templates/targetproduct.html
codemeta2html/templates/toc.html
codemeta2html/templates/validationrating.html