Metadata-Version: 2.2
Name: codemeta2html
Version: 0.2.0
Summary: Convert software metadata in codemeta to html for visualisation
Home-page: https://github.com/proycon/codemeta2html
Author: Maarten van Gompel
Author-email: proycon@anaproy.nl
License: GPL-3.0-only
Keywords: software metadata,codemeta,schema.org,rdf,linked data
Classifier: Development Status :: 5 - Production/Stable
Classifier: Topic :: Software Development
Classifier: Programming Language :: Python :: 3.6
Classifier: Programming Language :: Python :: 3.7
Classifier: Programming Language :: Python :: 3.8
Classifier: Programming Language :: Python :: 3.9
Classifier: Programming Language :: Python :: 3.10
Classifier: Programming Language :: Python :: 3.11
Classifier: Operating System :: POSIX
Classifier: Intended Audience :: Developers
Classifier: License :: OSI Approved :: GNU General Public License v3 (GPLv3)
License-File: LICENSE
Requires-Dist: codemetapy>=3.0.0
Requires-Dist: Jinja2>=2.9
Requires-Dist: rdflib
Dynamic: author
Dynamic: author-email
Dynamic: classifier
Dynamic: description
Dynamic: description-content-type
Dynamic: home-page
Dynamic: keywords
Dynamic: license
Dynamic: requires-dist
Dynamic: summary
